roku/__init__.py
roku/core.py
roku/discovery.py
roku/proxy.py
roku/server.py
roku/util.py
roku/emulator/__init__.py
roku/emulator/core.py
roku/tests/__init__.py
roku/tests/test_roku.py
roku-3.2.dist-info/LICENSE
roku-3.2.dist-info/METADATA
roku-3.2.dist-info/WHEEL
roku-3.2.dist-info/top_level.txt
roku-3.2.dist-info/RECORD
