Metadata-Version: 2.1
Name: roku
Version: 3.2
Summary: Client for the Roku media player
Home-page: https://github.com/jcarbaugh/python-roku
Author: Jeremy Carbaugh
Author-email: jcarbaugh@gmail.com
License: BSD License
Platform: any
Classifier: Development Status :: 5 - Production/Stable
Classifier: Intended Audience :: Developers
Classifier: License :: OSI Approved :: BSD License
Classifier: Natural Language :: English
Classifier: Programming Language :: Python
Classifier: Programming Language :: Python :: 3.6
Classifier: Programming Language :: Python :: 3.7
Classifier: Programming Language :: Python :: 3.8
Requires-Dist: lxml (<5)
Requires-Dist: requests (<3)
Requires-Dist: six
